pretalx_youtube/__init__.py
pretalx_youtube/api.py
pretalx_youtube/apps.py
pretalx_youtube/forms.py
pretalx_youtube/models.py
pretalx_youtube/recording.py
pretalx_youtube/signals.py
pretalx_youtube/urls.py
pretalx_youtube/views.py
pretalx_youtube/locale/django.pot
pretalx_youtube/locale/ar/LC_MESSAGES/django.mo
pretalx_youtube/locale/ar/LC_MESSAGES/django.po
pretalx_youtube/locale/bg/LC_MESSAGES/django.mo
pretalx_youtube/locale/bg/LC_MESSAGES/django.po
pretalx_youtube/locale/ca/LC_MESSAGES/django.mo
pretalx_youtube/locale/ca/LC_MESSAGES/django.po
pretalx_youtube/locale/cs/LC_MESSAGES/django.mo
pretalx_youtube/locale/cs/LC_MESSAGES/django.po
pretalx_youtube/locale/de_DE/LC_MESSAGES/django.mo
pretalx_youtube/locale/de_DE/LC_MESSAGES/django.po
pretalx_youtube/locale/de_Formal/LC_MESSAGES/django.mo
pretalx_youtube/locale/de_Formal/LC_MESSAGES/django.po
pretalx_youtube/locale/el/LC_MESSAGES/django.mo
pretalx_youtube/locale/el/LC_MESSAGES/django.po
pretalx_youtube/locale/es/LC_MESSAGES/django.mo
pretalx_youtube/locale/es/LC_MESSAGES/django.po
pretalx_youtube/locale/es_MX/LC_MESSAGES/django.mo
pretalx_youtube/locale/es_MX/LC_MESSAGES/django.po
pretalx_youtube/locale/fr_FR/LC_MESSAGES/django.mo
pretalx_youtube/locale/fr_FR/LC_MESSAGES/django.po
pretalx_youtube/locale/id/LC_MESSAGES/django.mo
pretalx_youtube/locale/id/LC_MESSAGES/django.po
pretalx_youtube/locale/it/LC_MESSAGES/django.mo
pretalx_youtube/locale/it/LC_MESSAGES/django.po
pretalx_youtube/locale/ja_JP/LC_MESSAGES/django.mo
pretalx_youtube/locale/ja_JP/LC_MESSAGES/django.po
pretalx_youtube/locale/ko/LC_MESSAGES/django.mo
pretalx_youtube/locale/ko/LC_MESSAGES/django.po
pretalx_youtube/locale/nl/LC_MESSAGES/django.mo
pretalx_youtube/locale/nl/LC_MESSAGES/django.po
pretalx_youtube/locale/pl/LC_MESSAGES/django.mo
pretalx_youtube/locale/pl/LC_MESSAGES/django.po
pretalx_youtube/locale/pt_BR/LC_MESSAGES/django.mo
pretalx_youtube/locale/pt_BR/LC_MESSAGES/django.po
pretalx_youtube/locale/pt_PT/LC_MESSAGES/django.mo
pretalx_youtube-2.4.0.dist-info/licenses/LICENSE
pretalx_youtube-2.4.0.dist-info/METADATA
pretalx_youtube-2.4.0.dist-info/WHEEL
pretalx_youtube-2.4.0.dist-info/entry_points.txt
pretalx_youtube-2.4.0.dist-info/top_level.txt
pretalx_youtube-2.4.0.dist-info/RECORD
