Metadata-Version: 2.4
Name: pretalx-youtube
Version: 2.4.0
Summary: Static youtube for pretalx, e.g. information, venue listings, a Code of Conduct, etc.
Author-email: Tobias Kunze <r@rixx.de>
Maintainer-email: Tobias Kunze <r@rixx.de>
License: Apache Software License
Project-URL: homepage, https://github.com/pretalx/pretalx-youtube
Project-URL: repository, https://github.com/pretalx/pretalx-youtube.git
Keywords: pretalx
License-File: LICENSE
Dynamic: license-file
